Metadata-Version: 2.1
Name: django-pgviews-schema
Version: 0.0.3
Summary: Create and manage Postgres SQL Views in Django
Home-page: https://github.com/pedrohsbarbosa99/django-pgviews-schema
Author: Pedro Barbosa
Author-email: pedrohsbarbosa99@gmail.com
License: Public Domain
Platform: UNKNOWN
Classifier: Development Status :: 2 - Pre-Alpha
Classifier: Programming Language :: Python
Classifier: Programming Language :: Python :: 3
Classifier: Programming Language :: Python :: 3.7
Classifier: Programming Language :: Python :: 3.8
Classifier: Programming Language :: Python :: 3.9
Classifier: Programming Language :: Python :: 3.10
Classifier: Programming Language :: Python :: 3.11
Classifier: Framework :: Django
Classifier: Framework :: Django :: 3.2
Classifier: Framework :: Django :: 4.0
Classifier: Framework :: Django :: 4.1
Classifier: Framework :: Django :: 4.2
